<items>

<dir>
<name>MosalsalatHD</name>
<type>videos</type>
<thumbnail>https://yt3.ggpht.com/-v6fE-NdV-Vs/AAAAAAAAAAI/AAAAAAAAAAA/mUa_OFhsWJc/s100-c-k-no/photo.jpg
</thumbnail>
<youtubeuser>MosalsalatHD</youtubeuser>
</dir>

<dir>
<name>rafee8elrouh</name>
<type>videos</type>
<thumbnail>https://yt3.ggpht.com/-pZFxlmJLuVE/AAAAAAAAAAI/AAAAAAAAAAA/IUblnyjFhRo/s100-c-k-no/photo.jpg</thumbnail>
<youtubeuser>rafee8elrouh</youtubeuser>
</dir>

<dir>
<name>RaafatElHaggan</name>
<type>videos</type>
<thumbnail>https://yt3.ggpht.com/-ZkY3wDiJJ_E/AAAAAAAAAAI/AAAAAAAAAAA/_olSrWEyJN4/s176-c-k-no/photo.jpg</thumbnail>
<youtubeuser>RaafatElHaggan</youtubeuser>
</dir>

<dir>
<name>Ramadanak</name>
<type>playlist</type>
<thumbnail>https://yt3.ggpht.com/-qYYvygXlhuk/AAAAAAAAAAI/AAAAAAAAAAA/gA-mJ7udhUo/s100-c-k-no/photo.jpg</thumbnail>
<youtubeuser>Ramadanak</youtubeuser>
</dir>

<dir>
<name>manahel</name>
<type>playlist</type>
<thumbnail>http://i1.ytimg.com/vi/kbko6TvUTro/default.jpg</thumbnail>
<youtubeuser>media4arab1</youtubeuser>
</dir>

<dir>
<name>films</name>
<type>videos</type>
<thumbnail>https://yt3.ggpht.com/-RObAnqTsoHM/AAAAAAAAAAI/AAAAAAAAAAA/8l39_ux5ppg/s100-c-k-no/photo.jpg</thumbnail>
<youtubeuser>MegaTunisiaNews</youtubeuser>
</dir>

<dir>
<name>TunMediaCenter</name>
<type>videos</type>
<thumbnail>https://yt3.ggpht.com/-c065rOOTLTw/AAAAAAAAAAI/AAAAAAAAAAA/0bXd4y7TmXc/s100-c-k-no/photo.jpg</thumbnail>
<youtubeuser>TunMediaCenter</youtubeuser>
</dir>

<dir>
<name>series</name>
<type>videos</type>
<thumbnail>https://yt3.ggpht.com/-goPkt0e47wc/AAAAAAAAAAI/AAAAAAAAAAA/HckxRukXGAo/s100-c-k-no/photo.jpg</thumbnail>
<channelid>UC-54AUQE1B5TKCFFdDiJR7Q</channelid>
</dir>

<dir>
<name>amirati anti</name>
<type>videos</type>
<thumbnail>https://yt3.ggpht.com/-wBqFJsAl2Y0/AAAAAAAAAAI/AAAAAAAAAAA/3nsB743wPio/s100-c-k-no/photo.jpg</thumbnail>
<channelid>UCbBkNCoA5wop1-ZAnvCIkcA</channelid>
</dir>

</items>