<items>

<dir>
<name>Acta0m</name>
<type>videos</type>
<thumbnail>http://i.imgur.com/4vWU5xX.png</thumbnail>
<youtubeuser>Acta0m</youtubeuser>
</dir>

<dir>
<name></name>
<link></link>
<thumbnail>http://i.imgur.com/4vWU5xX.png</thumbnail>
</dir>

<dir>
<name></name>
<link></link>
<thumbnail>http://i.imgur.com/4vWU5xX.png</thumbnail>
</dir>

<dir>
<name></name>
<link></link>
<thumbnail>http://i.imgur.com/4vWU5xX.png</thumbnail>
</dir>

<dir>
<name></name>
<link></link>
<thumbnail>http://i.imgur.com/4vWU5xX.png</thumbnail>
</dir>
</items>
