<items>
#######################################################################################################################################
<poster>ShahidTube by Zombi floow me on twitter @zombixbmc</poster>
<fanart></fanart>
#######################################################################################################################################

<dir>
<name>Videos</name>
<link>http://gdata.youtube.com/feeds/api/users/telvzatvchannel/uploads</link>
<thumbnail>https://yt3.ggpht.com/-JXVk9MIa5gk/AAAAAAAAAAI/AAAAAAAAAAA/G178CZuneZA/s100-c-k-no/photo.jpg</thumbnail>
</dir>

<dir>
<name>Playlists</name>
<link>http://gdata.youtube.com/feeds/api/users/telvzatvchannel/playlists</link>
<thumbnail>https://yt3.ggpht.com/-JXVk9MIa5gk/AAAAAAAAAAI/AAAAAAAAAAA/G178CZuneZA/s100-c-k-no/photo.jpg</thumbnail>
</dir>



</items>
